limitor/__init__.py
limitor/base.py
limitor/configs.py
limitor/utils.py
limitor/extra/__init__.py
limitor/extra/leaky_bucket/__init__.py
limitor/extra/leaky_bucket/core.py
limitor/generic_cell_rate/__init__.py
limitor/generic_cell_rate/core.py
limitor/leaky_bucket/__init__.py
limitor/leaky_bucket/core.py
limitor/token_bucket/__init__.py
limitor/token_bucket/core.py
limitor-0.3.3.dist-info/licenses/LICENSE
limitor-0.3.3.dist-info/METADATA
limitor-0.3.3.dist-info/WHEEL
limitor-0.3.3.dist-info/top_level.txt
limitor-0.3.3.dist-info/RECORD
