Metadata-Version: 2.4
Name: limitor
Version: 0.3.3
Summary: Rate limiting package
Author-email: Jordan Rinder <jordan.rinder@gmail.com>
Maintainer-email: Jordan Rinder <jordan.rinder@gmail.com>
Project-URL: Homepage, https://github.com/jrinder42/rate-limit
Project-URL: Source, https://github.com/jrinder42/rate-limit
Keywords: Rate Limit
Classifier: Programming Language :: Python
Classifier: Programming Language :: Python :: 3
Classifier: Programming Language :: Python :: 3.12
Classifier: Programming Language :: Python :: 3.13
Requires-Python: >=3.12
License-File: LICENSE
Requires-Dist: pytest-asyncio>=1.2.0
Dynamic: license-file
